testcontainers/selenium/__init__.py
tests/test_selenium.py
testcontainers_selenium-0.0.1rc1.dist-info/METADATA
testcontainers_selenium-0.0.1rc1.dist-info/WHEEL
testcontainers_selenium-0.0.1rc1.dist-info/top_level.txt
testcontainers_selenium-0.0.1rc1.dist-info/RECORD
